{"timestamp":1687473241,"version_static":"0.5.10884","version_runtime":"0.5.10884","duration":817055,"commit_sha":"ba19195","commit_timestamp":1687465345,"files":151,"rbi_files":38,"modules":475,"classes":5852,"singleton_classes":3388,"methods_without_sig":21698,"methods_with_sig":1773,"calls_untyped":1143,"calls_typed":4620,"sigils":{"false":2,"true":69,"strict":80},"methods_with_sig_excluding_rbis":331,"methods_without_sig_excluding_rbis":540,"sigils_excluding_rbis":{"false":1,"true":35,"strict":79}}